{
  "clear_yes": [
    "да, покупка может быть удачной",
    "да, знак не спорит с этим приобретением",
    "да, эта трата выглядит оправданной",
    "да, покупка может принести пользу, а не пустой расход",
    "да, линия этой вещи выглядит рабочей"
  ],
  "lean_yes": [
    "скорее да, чем нет: покупка выглядит разумной",
    "приобретение возможно, если оно не сделано в спешке",
    "знак склоняется к покупке, хотя с условием внимательного выбора",
    "трата может быть полезной, если не переплатить за лишнее",
    "эта вещь скорее несёт пользу, чем сожаление"
  ],
  "clear_no": [
    "нет, покупка сейчас не выглядит удачной",
    "нет, трата здесь скорее ослабит, чем усилит",
    "нет, знак не поддерживает это приобретение",
    "нет, вещь может оказаться не такой ценной, как кажется",
    "нет, линия покупки выглядит сомнительной"
  ],
  "uncertain": [
    "покупка зависит от цены, качества и настоящей необходимости",
    "знак не спорит с самой идеей, но спорит с деталями",
    "приобретение возможно, хотя риск ошибки в выборе ещё есть",
    "картина не даёт полного запрета, но требует осторожности",
    "исход этой траты зависит от того, насколько она осмысленна"
  ],
  "guidance": [
    "смотри не на желание купить, а на то, как вещь будет служить потом",
    "хорошая покупка держится пользой дольше, чем эмоцией первого дня",
    "сравни цену не только с кошельком, но и с реальной нуждой",
    "если вещь важна, проверь её дважды, а не только захоти"
  ],
  "warning": [
    "не путай импульс и необходимость",
    "опасно покупать только ради мгновенного облегчения или удовольствия",
    "если выбор мутный, лучше задержать покупку, чем потом платить дважды",
    "самая коварная трата — та, что кажется маленькой и безобидной"
  ]
}