{
  "clear_yes": [
    "да, здесь линия выглядит достаточно честной",
    "да, этот человек скорее говорит правду, чем скрывает её",
    "да, знак не показывает явной лжи",
    "да, в его словах есть опора на реальность",
    "да, сейчас его речь ближе к правде, чем к игре"
  ],
  "lean_yes": [
    "скорее да, чем нет: он не выглядит явным лжецом",
    "правда в его словах есть, хотя не вся",
    "он не врёт прямо, но может недоговаривать",
    "линия честности держится, но не без тени",
    "скорее искренность, чем обман, хотя не без осторожности"
  ],
  "clear_no": [
    "нет, здесь знак не даёт полной честности",
    "нет, в его словах есть искажение",
    "нет, эта линия не выглядит прямой",
    "нет, он скрывает больше, чем показывает",
    "нет, правды здесь меньше, чем хотелось бы"
  ],
  "uncertain": [
    "он может смешивать правду с удобной для себя версией",
    "картина показывает не чистую ложь, а частичное сокрытие",
    "здесь не всё сказано прямо, но и не всё придумано",
    "честность колеблется между откровенностью и защитой",
    "линия речи не совсем ровная, но и не полностью ложная"
  ],
  "guidance_act": [
    "проверяй правду по поступкам и деталям",
    "не опирайся только на сказанное",
    "задай уточняющий вопрос и смотри, как изменится линия",
    "сопоставь слова с тем, что он делал раньше"
  ],
  "warning": [
    "недосказанность иногда опаснее прямой лжи",
    "будь осторожен там, где слова слишком удобны",
    "не принимай уверенный тон за доказательство правды",
    "ложь чаще всего прячется не в громких словах, а в пропущенных частях"
  ]
}